{
    "1.130.0": {
        "date": "October 2024",
        "notes": [
            {
                "id": "8eab5316c039c11a031b9fb5bf602a756305459b",
                "type": "FIX",
                "text": " ValueListProvider: correct description when multiple requests are send"
            },
            {
                "id": "2ada990f3c7b365ccf5ccee1cee2af0268ec5f0e",
                "type": "FIX",
                "text": " ValueHelpDialog: add in ignoredFields description only if the key column is in ValueList",
                "references": [
                    {
                        "type": "BCP",
                        "reference": "2380137505"
                    }
                ]
            },
            {
                "id": "2f187592d3c818be924ec2fcd48ccb682ea0e3e5",
                "type": "FIX",
                "text": " SmartField: renderWhitespace property is now applied when creating text controls"
            },
            {
                "id": "981d4577ac4c28292c7b9395cde2165301586e31",
                "type": "FIX",
                "text": " SmartField: Description is now shown on context changed"
            },
            {
                "id": "29e00658d9c70602160efb11935593a1edc24fb1",
                "type": "FEATURE",
                "text": " SmartFilterBar: DateRange support new options"
            },
            {
                "id": "061e965e6c28c86ea391161e37c0c535a4c78906",
                "type": "FIX",
                "text": " SmartField: FunctionImport field with wrong value list restriction"
            },
            {
                "id": "6ae3e8a5eb59f4e0ecfe23c6b9060e18a529edb7",
                "type": "FIX",
                "text": " ValueListProvider: model value of single filter field is correctly updated when there is validation request"
            },
            {
                "id": "c1b42235157ffcbcb579e56a41a209d5782ef9a7",
                "type": "FEATURE",
                "text": " SmartField: Supports lazy loading of function import parameters value help metadata"
            },
            {
                "id": "f8543d709c034a0490dd6ae7705c4391ad00baad",
                "type": "FIX",
                "text": " ValueListProvider: type ahead no longer throws exception"
            },
            {
                "id": "d9090915352617b17f6405f7e5afe62ac1638c23",
                "type": "FIX",
                "text": " ValueHelpDialog: Add button in header now has correct announcement"
            },
            {
                "id": "cde913af6f9551fdcdc6607ca8d7e65bfc8c8170",
                "type": "FIX",
                "text": " SmartField: On items load the ComboBox now applies the already set value on specific case"
            },
            {
                "id": "238ceee7bf7ae84bdef454f5735e6130a311d61b",
                "type": "FIX",
                "text": " SmartField now fires change event with opened suggestions"
            }
        ]
    },
    "1.130.1": {
        "date": "November 2024",
        "notes": [
            {
                "id": "683766d2a19bf6b1c9644dce4197439162fc424c",
                "type": "FIX",
                "text": " SmartVariantManagementModel: updateView take care of standard variant"
            },
            {
                "id": "e2c1d143ba532eb9fbf26183e15031b0771fc4de",
                "type": "FIX",
                "text": " We now ensure that for the new tokens created in SmartMultiInput, the correct context is returned"
            },
            {
                "id": "990a8c711c7f1724d7d6ed1949abeb16827eed6f",
                "type": "FIX",
                "text": " FilterBar: Order of filter items is now correct"
            },
            {
                "id": "eb85be5ff2f7eef4f3b78bcb1212a14b18bf1b89",
                "type": "FIX",
                "text": " SmartField: 0 value for NUMC with TextArrangement is now not shown initially"
            }
        ]
    },
    "1.130.2": {
        "date": "December 2024",
        "notes": [
            {
                "id": "772b380623c83646efa99a434926a1008d272a02",
                "type": "FIX",
                "text": " SmartField: Value is no longer cleared when binding context is changed"
            },
            {
                "id": "a346fb4ab0277d4b21a096bfcbc871f01302c205",
                "type": "FIX",
                "text": " FilterBar: changing localization now recreates the buttons with reloaded resource buntle"
            },
            {
                "id": "6f7f9c2e30199b665999b3870413d46c7fdcc140",
                "type": "FIX",
                "text": " ValueHelpDialog: add in ignoredFields description, only if the key column is in ValueList entity set and is visible"
            },
            {
                "id": "37b4dd19b89bbe5df49f977dedc2a92bdfa7a024",
                "type": "FIX",
                "text": " SmartFilterBar: SFBMultiComboBox now updates the model properly on suggested item selection"
            },
            {
                "id": "b2658e3329aea8c4126fb2c14e7db2f3caaf7fa4",
                "type": "FIX",
                "text": " ValueListProvider: The correct filter field description is now applied when multiple validation requests are submitted"
            },
            {
                "id": "6665cf38d201deac5596b87036d30f8ccb751632",
                "type": "FIX",
                "text": " SmartField: description is now correctly handled in display mode"
            },
            {
                "id": "30d47e1c9287334ac1e97f7d54718c1e9c92617e",
                "type": "FIX",
                "text": " SmartFilterBar: variant now stores info for condition type filters having default operation"
            },
            {
                "id": "1cd4ce562b9e18b16559c2c8fb8a8878a9a34b89",
                "type": "FIX",
                "text": " FilterProvider: show all filters button is now correctly set according to the configurations"
            }
        ]
    },
    "1.130.3": {
        "date": "January 2025",
        "notes": [
            {
                "id": "bf124575277e7764cd262d947572c5d13c9b98fc",
                "type": "FIX",
                "text": " SmartField: maxLength handling with TextOnly and isDigitalSequence"
            },
            {
                "id": "1a5b61aa24840771d1e2f8dff5365746bbaddd3d",
                "type": "FIX",
                "text": " SmartFilterBar: Unable to remove tokens in adapt filters dialog scenario is now fixed"
            },
            {
                "id": "91530bc7c14e6fe310b3c95a47a8b99f20877a1e",
                "type": "FIX",
                "text": " SmartField: Description is now not fetched when the control is hidden"
            }
        ]
    }
}