{
    "1.40.0": {
        "date": "June 2016",
        "notes": [
            {
                "id": "71ba9564a250b49b1e52762b81b08114b866e502",
                "type": "FIX",
                "text": "RichTextEditor: Exceptions in IE 11 QUnit Test",
                "references": [
                    {
                        "type": "BCP",
                        "reference": "1670320477"
                    }
                ]
            },
            {
                "id": "6ae0b460f89205f2ec29b8cd9fae4e4125ba1850",
                "type": "FIX",
                "text": "RichTextEditor: Reduced Number of Initializations",
                "references": [
                    {
                        "type": "BCP",
                        "reference": "1580170403"
                    },
                    {
                        "type": "BCP",
                        "reference": "1670047554"
                    },
                    {
                        "type": "BCP",
                        "reference": "1670071388"
                    }
                ]
            },
            {
                "id": "de4d75788a49ff0b49e0c49240bc9c8a423bf4fc",
                "type": "FIX",
                "text": "RichTextEditor: TinyMCE3 show initial value",
                "references": [
                    {
                        "type": "BCP",
                        "reference": "002075129500001130642016"
                    }
                ]
            }
        ]
    }
}